Workbook

Sheet Final Comparison
A1: HP ZBook 8 G1i 16-inch Mobile Workstation | Vendor Decision Dashboard
A2: 10 units • Intel Core Ultra 7 255H • 32GB DDR5 • 1TB SSD • Windows 11 Pro • 3-year warranty + ADP • Final review: 24-Aug-2026
A3: VENDOR DECISION SUMMARY
A4: Rank | B4: Vendor | C4: Grand Total Incl. GST | D4: Premium vs Lowest | E4: Payment / Delivery | F4: Compliance / Action
A5: =RANK(C5,$C$5:$C$8,1) -> 1 | B5: ='Quote Details'!A6 -> IT World India Tech Pvt. Ltd. | C5: ='Quote Details'!K6 -> 2054380 | D5: =C5-MIN($C$5:$C$8) -> 0 | E5: ='Quote Details'!O6&CHAR(10)&'Quote Details'!N6 -> 100% advance with PO | Valid through 22-Aug-2026 1 week after PO | F5: CONDITIONAL BEST VALUE Confirm Hardware Hash CSV, exact OEM part number, stock, nil freight and refreshed validity.
A6: =RANK(C6,$C$5:$C$8,1) -> 2 | B6: ='Quote Details'!A7 -> GNR Solution Pvt. Ltd. | C6: ='Quote Details'!K7 -> 2185360 | D6: =C6-MIN($C$5:$C$8) -> 130980 | E6: ='Quote Details'!O7&CHAR(10)&'Quote Details'!N7 -> 30 days | Valid 3 days 4-5 days from PO | F6: BEST CREDIT TERMS 30-day payment and fastest stated delivery; confirm hash and freight outside Pune.
A7: =RANK(C7,$C$5:$C$8,1) -> 3 | B7: ='Quote Details'!A8 -> Turbonet Systems Pvt. Ltd. | C7: ='Quote Details'!K8 -> 2208358.2 | D7: =C7-MIN($C$5:$C$8) -> 153978.2 | E7: ='Quote Details'!O8&CHAR(10)&'Quote Details'!N8 -> 100% advance | Valid 2 days 5-7 days after PO and payment | F7: THIRD-LOWEST Confirm mouse, Hardware Hash, exact part number, freight and refreshed validity.
A8: =RANK(C8,$C$5:$C$8,1) -> 4 | B8: ='Quote Details'!A9 -> HP India Sales Pvt. Ltd. | C8: ='Quote Details'!K9 -> 2296716.6 | D8: =C8-MIN($C$5:$C$8) -> 242336.6 | E8: ='Quote Details'!O9&CHAR(10)&'Quote Details'!N9 -> 100% advance | Expired 23-Aug-2026 1-2 weeks after clean PO/payment; email says within 7 days | F8: MOST COMPLETE / LOW RISK Hash, wireless mouse and backpack explicitly included; resolve delivery wording and validity.
A9: DECISION GUIDANCE
A10: 1. Select IT World for the lowest acquisition cost: ₹2,054,380 including GST. 2. Do not release the PO until Hardware Hash CSV, exact OEM part number/configuration, stock, nil freight and renewed validity are confirmed in writing. 3. Select HP India if scope certainty and OEM-direct accountability justify a ₹242,336.60 premium. 4. Consider GNR when 30-day credit is more important than the absolute lowest price.
A14: TOTAL COST COMPARISON

Sheet Quote Details
A1: HP ZBook 8 G1i | Quote Details
A2: All prices for 10 units; amounts in INR
A5: Vendor | B5: Quote Date | C5: Quote Ref / Source | D5: OEM Part No. | E5: Qty | F5: Base Laptop Total Excl. GST | G5: ADP Total Excl. GST | H5: Accessories / Hash Excl. GST | I5: Total Excl. GST | J5: GST @ 18% | K5: Grand Total Incl. GST | L5: Unit Total Incl. GST | M5: Warranty | N5: Delivery | O5: Payment / Validity | P5: Notes
A6: IT World India Tech Pvt. Ltd. | B6: 46255 | C6: IT World_kforceHPZbookGli-21-08-2026.pdf | D6: Not stated | E6: 10 | F6: 1741000 | G6: 0 | H6: 0 | I6: =SUM(F6:H6) -> 1741000 | J6: =I6*18% -> 313380 | K6: =I6+J6 -> 2054380 | L6: =K6/E6 -> 205438 | M6: 3 years warranty with ADP | N6: 1 week after PO | O6: 100% advance with PO | Valid through 22-Aug-2026 | P6: All-inclusive line item states bag and wireless mouse. Hardware Hash is not stated in PDF. Email says there is no additional cost beyond quote, but obtain explicit hash confirmation.
A7: GNR Solution Pvt. Ltd. | B7: 46255 | C7: GNR_Quote_KForce_Laptop.pdf | D7: C1JP4PT | E7: 10 | F7: 1791000 | G7: 52500 | H7: 8500 | I7: =SUM(F7:H7) -> 1852000 | J7: =I7*18% -> 333360 | K7: =I7+J7 -> 2185360 | L7: =K7/E7 -> 218536 | M7: 3 years standard + 3 years ADP | N7: 4-5 days from PO | O7: 30 days | Valid 3 days | P7: USB mouse included in laptop line; backpack separate. Freight nominal at actual outside Pune. Hardware Hash not stated.
A8: Turbonet Systems Pvt. Ltd. | B8: 46255 | C8: Turbonet_Commercial_KFORCE...TSPL-2108.pdf | D8: Not stated | E8: 10 | F8: 1806500 | G8: 64990 | H8: 0 | I8: =SUM(F8:H8) -> 1871490 | J8: =I8*18% -> 336868.2 | K8: =I8+J8 -> 2208358.2 | L8: =K8/E8 -> 220835.82 | M8: 3 years standard + ADP support | N8: 5-7 days after PO and payment | O8: 100% advance | Valid 2 days | P8: Backpack stated. Mouse and Hardware Hash not stated. Freight at actual outside Mumbai.
A9: HP India Sales Pvt. Ltd. | B9: 46255 | C9: Quote 74585772479316 | D9: DF3K6PA | E9: 10 | F9: 1878000 | G9: 46000 | H9: 22370 | I9: =SUM(F9:H9) -> 1946370 | J9: =I9*18% -> 350346.6 | K9: =I9+J9 -> 2296716.6 | L9: =K9/E9 -> 229671.66 | M9: 3 years onsite + 3 years ADP | N9: 1-2 weeks after clean PO/payment; email says within 7 days | O9: 100% advance | Expired 23-Aug-2026 | P9: Accessories/hash: Hash ₹6,400 + mouse ₹6,630 + backpack ₹9,340. Door delivery. Stock available stated in email.
